cdhit_reader/__init__.py
cdhit_reader/_cli.py
cdhit_reader/_compare.py
cdhit_reader/_fasta.py
cdhit_reader/_reader.py
cdhit_reader/_testit.py
cdhit_reader/_version.py
cdhit_reader/test/__init__.py
cdhit_reader/test/aa.clstr
cdhit_reader/test/nt.clstr
cdhit_reader/test/test_clstr.py
cdhit_reader-0.2.0.dist-info/LICENSE.md
cdhit_reader-0.2.0.dist-info/METADATA
cdhit_reader-0.2.0.dist-info/WHEEL
cdhit_reader-0.2.0.dist-info/entry_points.txt
cdhit_reader-0.2.0.dist-info/top_level.txt
cdhit_reader-0.2.0.dist-info/zip-safe
cdhit_reader-0.2.0.dist-info/RECORD
