Metadata-Version: 2.1
Name: cdhit-reader
Version: 0.2.0
Summary: CD-HIT cluster parser
Home-page: https://github.com/telatin/cdhit-parser
Download-URL: https://github.com/telatin/cdhit-parser
Author: Andrea Telatin
Author-email: andrea.telatin@gmail.com
Maintainer: Andrea Telatin
Maintainer-email: andrea.telatin@gmail.com
License: MIT
Keywords: cd-hit,clustering,reader
Platform: Windows
Platform: MacOS
Platform: Linux
Classifier: Development Status :: 4 - Beta
Classifier: License :: OSI Approved :: MIT License
Classifier: Operating System :: OS Independent
Classifier: Programming Language :: Python
License-File: LICENSE.md
Requires-Dist: click (>=7.1.2)
Requires-Dist: importlib-resources (>=1.4.0)
Requires-Dist: more-itertools (>=8.4.0)
Requires-Dist: pytest (>=5.4.3)
Requires-Dist: xopen (>=1.0.1)
Provides-Extra: cli
Requires-Dist: plotille ; extra == 'cli'
